{"id":"../../models/userModel.js","dependencies":[{"name":"/Users/hieungannguyen/Dropbox/Mac/Documents/vn-tours/package.json","includedInParent":true,"mtime":1652461384140},{"name":"mongoose","loc":{"line":1,"column":25},"parent":"/Users/hieungannguyen/Dropbox/Mac/Documents/vn-tours/models/userModel.js","resolved":"/Users/hieungannguyen/Dropbox/Mac/Documents/vn-tours/node_modules/mongoose/dist/browser.umd.js"},{"name":"slugify","loc":{"line":2,"column":24},"parent":"/Users/hieungannguyen/Dropbox/Mac/Documents/vn-tours/models/userModel.js","resolved":"/Users/hieungannguyen/Dropbox/Mac/Documents/vn-tours/node_modules/slugify/slugify.js"},{"name":"validator","loc":{"line":3,"column":26},"parent":"/Users/hieungannguyen/Dropbox/Mac/Documents/vn-tours/models/userModel.js","resolved":"/Users/hieungannguyen/Dropbox/Mac/Documents/vn-tours/node_modules/validator/index.js"},{"name":"bcryptjs","loc":{"line":4,"column":23},"parent":"/Users/hieungannguyen/Dropbox/Mac/Documents/vn-tours/models/userModel.js","resolved":"/Users/hieungannguyen/Dropbox/Mac/Documents/vn-tours/node_modules/bcryptjs/dist/bcrypt.js"},{"name":"crypto","loc":{"line":5,"column":23},"parent":"/Users/hieungannguyen/Dropbox/Mac/Documents/vn-tours/models/userModel.js","resolved":"/Users/hieungannguyen/Dropbox/Mac/Documents/vn-tours/node_modules/crypto-browserify/index.js"}],"generated":{"js":"function _asyncToGenerator(fn) { return function () { var gen = fn.apply(this, arguments); return new Promise(function (resolve, reject) { function step(key, arg) { try { var info = gen[key](arg); var value = info.value; } catch (error) { reject(error); return; } if (info.done) { resolve(value); } else { return Promise.resolve(value).then(function (value) { step(\"next\", value); }, function (err) { step(\"throw\", err); }); } } return step(\"next\"); }); }; }\n\nvar mongoose = require('mongoose');\nvar slugify = require('slugify');\nvar validator = require('validator');\nvar bcrypt = require('bcryptjs');\nvar crypto = require('crypto');\n\nvar userSchema = new mongoose.Schema({\n    name: {\n        type: String,\n        require: [true, 'Name is required'],\n        trim: true\n    },\n    email: {\n        type: String,\n        require: [true, 'Email is required'],\n        unique: true,\n        lowercase: true,\n        validate: [validator.isEmail, 'Email is invalid']\n    },\n    photo: String,\n    role: {\n        type: String,\n        enum: ['user', 'guide', 'lead-guide', 'admin'],\n        default: 'user'\n    },\n    password: {\n        type: String,\n        require: [true, 'Password is required'],\n        minlength: [8, 'Password must have at least 8 characters'],\n        select: false\n    },\n    passwordConfirm: {\n        type: String,\n        require: [true, 'Password must match'],\n        validate: {\n            // only work on CREATE and SAVE\n            validator: function validator(el) {\n                return el === this.password;\n            },\n            message: 'Passwords are not the same'\n        }\n    },\n    passwordChangedAt: Date,\n    passwordResetToken: String,\n    passwordResetExpires: Date,\n    active: {\n        type: Boolean,\n        default: true,\n        select: false // not showing it to anyone\n    }\n});\n\nuserSchema.pre('save', function () {\n    var _ref = _asyncToGenerator( /*#__PURE__*/regeneratorRuntime.mark(function _callee(next) {\n        return regeneratorRuntime.wrap(function _callee$(_context) {\n            while (1) {\n                switch (_context.prev = _context.next) {\n                    case 0:\n                        if (this.isModified('password')) {\n                            _context.next = 2;\n                            break;\n                        }\n\n                        return _context.abrupt('return', next());\n\n                    case 2:\n                        _context.next = 4;\n                        return bcrypt.hash(this.password, 12);\n\n                    case 4:\n                        this.password = _context.sent;\n\n\n                        this.passwordConfirm = undefined; // not to be persisted to the database \n                        next();\n\n                    case 7:\n                    case 'end':\n                        return _context.stop();\n                }\n            }\n        }, _callee, this);\n    }));\n\n    return function (_x) {\n        return _ref.apply(this, arguments);\n    };\n}());\n\nuserSchema.pre('save', function (next) {\n    if (!this.isModified('password') || this.isNew) return next();\n\n    this.passwordChangedAt = Date.now() - 1000;\n    next();\n});\n\nuserSchema.pre(/^find/, function (next) {\n    // this points to the current query\n    this.find({ active: { $ne: false } });\n    next();\n});\n// instant function, available on all models \nuserSchema.methods.correctPassword = function () {\n    var _ref2 = _asyncToGenerator( /*#__PURE__*/regeneratorRuntime.mark(function _callee2(candidatePassword, userPassword) {\n        return regeneratorRuntime.wrap(function _callee2$(_context2) {\n            while (1) {\n                switch (_context2.prev = _context2.next) {\n                    case 0:\n                        _context2.next = 2;\n                        return bcrypt.compare(candidatePassword, userPassword);\n\n                    case 2:\n                        return _context2.abrupt('return', _context2.sent);\n\n                    case 3:\n                    case 'end':\n                        return _context2.stop();\n                }\n            }\n        }, _callee2, this);\n    }));\n\n    return function (_x2, _x3) {\n        return _ref2.apply(this, arguments);\n    };\n}();\n\nuserSchema.methods.changePasswordAfter = function (JWTTimestamp) {\n    if (this.passwordChangedAt) {\n        var changedTimestamp = parseInt(this.passwordChangedAt.getTime() / 1000, 10);\n\n        return JWTTimestamp < changedTimestamp; // token creation time < password change time -> password was changed!\n    }\n    return false; // the user hasn't changed the pass after this timestamp\n};\n\nuserSchema.methods.createPasswordResetToken = function () {\n    var resetToken = crypto.randomBytes(32).toString('hex');\n\n    this.passwordResetToken = crypto.createHash('sha256').update(resetToken).digest('hex');\n\n    console.log({ resetToken: resetToken }, this.passwordResetToken);\n\n    this.passwordResetExpires = Date.now() + 10 * 60 * 1000;\n\n    return resetToken;\n};\nvar User = mongoose.model('User', userSchema);\nmodule.exports = User;","map":{"mappings":[{"generated":{"line":3,"column":0},"source":"../../models/userModel.js","original":{"line":1,"column":0}},{"name":"mongoose","generated":{"line":3,"column":4},"source":"../../models/userModel.js","original":{"line":1,"column":6}},{"name":"require","generated":{"line":3,"column":15},"source":"../../models/userModel.js","original":{"line":1,"column":17}},{"generated":{"line":3,"column":23},"source":"../../models/userModel.js","original":{"line":1,"column":25}},{"generated":{"line":3,"column":33},"source":"../../models/userModel.js","original":{"line":1,"column":17}},{"generated":{"line":3,"column":34},"source":"../../models/userModel.js","original":{"line":1,"column":0}},{"generated":{"line":4,"column":0},"source":"../../models/userModel.js","original":{"line":2,"column":0}},{"name":"slugify","generated":{"line":4,"column":4},"source":"../../models/userModel.js","original":{"line":2,"column":6}},{"name":"require","generated":{"line":4,"column":14},"source":"../../models/userModel.js","original":{"line":2,"column":16}},{"generated":{"line":4,"column":22},"source":"../../models/userModel.js","original":{"line":2,"column":24}},{"generated":{"line":4,"column":31},"source":"../../models/userModel.js","original":{"line":2,"column":16}},{"generated":{"line":4,"column":32},"source":"../../models/userModel.js","original":{"line":2,"column":0}},{"generated":{"line":5,"column":0},"source":"../../models/userModel.js","original":{"line":3,"column":0}},{"name":"validator","generated":{"line":5,"column":4},"source":"../../models/userModel.js","original":{"line":3,"column":6}},{"name":"require","generated":{"line":5,"column":16},"source":"../../models/userModel.js","original":{"line":3,"column":18}},{"generated":{"line":5,"column":24},"source":"../../models/userModel.js","original":{"line":3,"column":26}},{"generated":{"line":5,"column":35},"source":"../../models/userModel.js","original":{"line":3,"column":18}},{"generated":{"line":5,"column":36},"source":"../../models/userModel.js","original":{"line":3,"column":0}},{"generated":{"line":6,"column":0},"source":"../../models/userModel.js","original":{"line":4,"column":0}},{"name":"bcrypt","generated":{"line":6,"column":4},"source":"../../models/userModel.js","original":{"line":4,"column":6}},{"name":"require","generated":{"line":6,"column":13},"source":"../../models/userModel.js","original":{"line":4,"column":15}},{"generated":{"line":6,"column":21},"source":"../../models/userModel.js","original":{"line":4,"column":23}},{"generated":{"line":6,"column":31},"source":"../../models/userModel.js","original":{"line":4,"column":15}},{"generated":{"line":6,"column":32},"source":"../../models/userModel.js","original":{"line":4,"column":0}},{"generated":{"line":7,"column":0},"source":"../../models/userModel.js","original":{"line":5,"column":0}},{"name":"crypto","generated":{"line":7,"column":4},"source":"../../models/userModel.js","original":{"line":5,"column":6}},{"name":"require","generated":{"line":7,"column":13},"source":"../../models/userModel.js","original":{"line":5,"column":15}},{"generated":{"line":7,"column":21},"source":"../../models/userModel.js","original":{"line":5,"column":23}},{"generated":{"line":7,"column":29},"source":"../../models/userModel.js","original":{"line":5,"column":15}},{"generated":{"line":7,"column":30},"source":"../../models/userModel.js","original":{"line":5,"column":0}},{"generated":{"line":9,"column":0},"source":"../../models/userModel.js","original":{"line":7,"column":0}},{"name":"userSchema","generated":{"line":9,"column":4},"source":"../../models/userModel.js","original":{"line":7,"column":6}},{"generated":{"line":9,"column":17},"source":"../../models/userModel.js","original":{"line":7,"column":19}},{"name":"mongoose","generated":{"line":9,"column":21},"source":"../../models/userModel.js","original":{"line":7,"column":23}},{"name":"Schema","generated":{"line":9,"column":30},"source":"../../models/userModel.js","original":{"line":7,"column":32}},{"generated":{"line":9,"column":36},"source":"../../models/userModel.js","original":{"line":7,"column":19}},{"generated":{"line":9,"column":37},"source":"../../models/userModel.js","original":{"line":7,"column":39}},{"name":"name","generated":{"line":10,"column":0},"source":"../../models/userModel.js","original":{"line":8,"column":4}},{"generated":{"line":10,"column":10},"source":"../../models/userModel.js","original":{"line":8,"column":10}},{"name":"type","generated":{"line":11,"column":0},"source":"../../models/userModel.js","original":{"line":9,"column":8}},{"name":"String","generated":{"line":11,"column":14},"source":"../../models/userModel.js","original":{"line":9,"column":14}},{"generated":{"line":11,"column":20},"source":"../../models/userModel.js","original":{"line":8,"column":10}},{"name":"require","generated":{"line":12,"column":0},"source":"../../models/userModel.js","original":{"line":10,"column":8}},{"generated":{"line":12,"column":17},"source":"../../models/userModel.js","original":{"line":10,"column":17}},{"generated":{"line":12,"column":18},"source":"../../models/userModel.js","original":{"line":10,"column":18}},{"generated":{"line":12,"column":22},"source":"../../models/userModel.js","original":{"line":10,"column":17}},{"generated":{"line":12,"column":24},"source":"../../models/userModel.js","original":{"line":10,"column":24}},{"generated":{"line":12,"column":42},"source":"../../models/userModel.js","original":{"line":10,"column":17}},{"generated":{"line":12,"column":43},"source":"../../models/userModel.js","original":{"line":8,"column":10}},{"name":"trim","generated":{"line":13,"column":0},"source":"../../models/userModel.js","original":{"line":11,"column":8}},{"generated":{"line":13,"column":14},"source":"../../models/userModel.js","original":{"line":11,"column":14}},{"generated":{"line":14,"column":0},"source":"../../models/userModel.js","original":{"line":8,"column":10}},{"generated":{"line":14,"column":5},"source":"../../models/userModel.js","original":{"line":7,"column":39}},{"name":"email","generated":{"line":15,"column":0},"source":"../../models/userModel.js","original":{"line":13,"column":4}},{"generated":{"line":15,"column":11},"source":"../../models/userModel.js","original":{"line":13,"column":11}},{"name":"type","generated":{"line":16,"column":0},"source":"../../models/userModel.js","original":{"line":14,"column":8}},{"name":"String","generated":{"line":16,"column":14},"source":"../../models/userModel.js","original":{"line":14,"column":14}},{"generated":{"line":16,"column":20},"source":"../../models/userModel.js","original":{"line":13,"column":11}},{"name":"require","generated":{"line":17,"column":0},"source":"../../models/userModel.js","original":{"line":15,"column":8}},{"generated":{"line":17,"column":17},"source":"../../models/userModel.js","original":{"line":15,"column":17}},{"generated":{"line":17,"column":18},"source":"../../models/userModel.js","original":{"line":15,"column":18}},{"generated":{"line":17,"column":22},"source":"../../models/userModel.js","original":{"line":15,"column":17}},{"generated":{"line":17,"column":24},"source":"../../models/userModel.js","original":{"line":15,"column":24}},{"generated":{"line":17,"column":43},"source":"../../models/userModel.js","original":{"line":15,"column":17}},{"generated":{"line":17,"column":44},"source":"../../models/userModel.js","original":{"line":13,"column":11}},{"name":"unique","generated":{"line":18,"column":0},"source":"../../models/userModel.js","original":{"line":16,"column":8}},{"generated":{"line":18,"column":16},"source":"../../models/userModel.js","original":{"line":16,"column":16}},{"generated":{"line":18,"column":20},"source":"../../models/userModel.js","original":{"line":13,"column":11}},{"name":"lowercase","generated":{"line":19,"column":0},"source":"../../models/userModel.js","original":{"line":17,"column":8}},{"generated":{"line":19,"column":19},"source":"../../models/userModel.js","original":{"line":17,"column":19}},{"generated":{"line":19,"column":23},"source":"../../models/userModel.js","original":{"line":13,"column":11}},{"name":"validate","generated":{"line":20,"column":0},"source":"../../models/userModel.js","original":{"line":18,"column":8}},{"generated":{"line":20,"column":18},"source":"../../models/userModel.js","original":{"line":18,"column":18}},{"name":"validator","generated":{"line":20,"column":19},"source":"../../models/userModel.js","original":{"line":18,"column":19}},{"name":"isEmail","generated":{"line":20,"column":29},"source":"../../models/userModel.js","original":{"line":18,"column":29}},{"generated":{"line":20,"column":36},"source":"../../models/userModel.js","original":{"line":18,"column":18}},{"generated":{"line":20,"column":38},"source":"../../models/userModel.js","original":{"line":18,"column":38}},{"generated":{"line":20,"column":56},"source":"../../models/userModel.js","original":{"line":18,"column":18}},{"generated":{"line":21,"column":0},"source":"../../models/userModel.js","original":{"line":13,"column":11}},{"generated":{"line":21,"column":5},"source":"../../models/userModel.js","original":{"line":7,"column":39}},{"name":"photo","generated":{"line":22,"column":0},"source":"../../models/userModel.js","original":{"line":20,"column":4}},{"name":"String","generated":{"line":22,"column":11},"source":"../../models/userModel.js","original":{"line":20,"column":11}},{"generated":{"line":22,"column":17},"source":"../../models/userModel.js","original":{"line":7,"column":39}},{"name":"role","generated":{"line":23,"column":0},"source":"../../models/userModel.js","original":{"line":21,"column":4}},{"generated":{"line":23,"column":10},"source":"../../models/userModel.js","original":{"line":21,"column":10}},{"name":"type","generated":{"line":24,"column":0},"source":"../../models/userModel.js","original":{"line":22,"column":8}},{"name":"String","generated":{"line":24,"column":14},"source":"../../models/userModel.js","original":{"line":22,"column":14}},{"generated":{"line":24,"column":20},"source":"../../models/userModel.js","original":{"line":21,"column":10}},{"name":"enum","generated":{"line":25,"column":0},"source":"../../models/userModel.js","original":{"line":23,"column":8}},{"generated":{"line":25,"column":14},"source":"../../models/userModel.js","original":{"line":23,"column":14}},{"generated":{"line":25,"column":15},"source":"../../models/userModel.js","original":{"line":23,"column":15}},{"generated":{"line":25,"column":21},"source":"../../models/userModel.js","original":{"line":23,"column":14}},{"generated":{"line":25,"column":23},"source":"../../models/userModel.js","original":{"line":23,"column":22}},{"generated":{"line":25,"column":30},"source":"../../models/userModel.js","original":{"line":23,"column":14}},{"generated":{"line":25,"column":32},"source":"../../models/userModel.js","original":{"line":23,"column":30}},{"generated":{"line":25,"column":44},"source":"../../models/userModel.js","original":{"line":23,"column":14}},{"generated":{"line":25,"column":46},"source":"../../models/userModel.js","original":{"line":23,"column":44}},{"generated":{"line":25,"column":53},"source":"../../models/userModel.js","original":{"line":23,"column":14}},{"generated":{"line":25,"column":54},"source":"../../models/userModel.js","original":{"line":21,"column":10}},{"name":"default","generated":{"line":26,"column":0},"source":"../../models/userModel.js","original":{"line":24,"column":8}},{"generated":{"line":26,"column":17},"source":"../../models/userModel.js","original":{"line":24,"column":17}},{"generated":{"line":27,"column":0},"source":"../../models/userModel.js","original":{"line":21,"column":10}},{"generated":{"line":27,"column":5},"source":"../../models/userModel.js","original":{"line":7,"column":39}},{"name":"password","generated":{"line":28,"column":0},"source":"../../models/userModel.js","original":{"line":26,"column":4}},{"generated":{"line":28,"column":14},"source":"../../models/userModel.js","original":{"line":26,"column":14}},{"name":"type","generated":{"line":29,"column":0},"source":"../../models/userModel.js","original":{"line":27,"column":8}},{"name":"String","generated":{"line":29,"column":14},"source":"../../models/userModel.js","original":{"line":27,"column":14}},{"generated":{"line":29,"column":20},"source":"../../models/userModel.js","original":{"line":26,"column":14}},{"name":"require","generated":{"line":30,"column":0},"source":"../../models/userModel.js","original":{"line":28,"column":8}},{"generated":{"line":30,"column":17},"source":"../../models/userModel.js","original":{"line":28,"column":17}},{"generated":{"line":30,"column":18},"source":"../../models/userModel.js","original":{"line":28,"column":18}},{"generated":{"line":30,"column":22},"source":"../../models/userModel.js","original":{"line":28,"column":17}},{"generated":{"line":30,"column":24},"source":"../../models/userModel.js","original":{"line":28,"column":24}},{"generated":{"line":30,"column":46},"source":"../../models/userModel.js","original":{"line":28,"column":17}},{"generated":{"line":30,"column":47},"source":"../../models/userModel.js","original":{"line":26,"column":14}},{"name":"minlength","generated":{"line":31,"column":0},"source":"../../models/userModel.js","original":{"line":29,"column":8}},{"generated":{"line":31,"column":19},"source":"../../models/userModel.js","original":{"line":29,"column":19}},{"generated":{"line":31,"column":20},"source":"../../models/userModel.js","original":{"line":29,"column":20}},{"generated":{"line":31,"column":21},"source":"../../models/userModel.js","original":{"line":29,"column":19}},{"generated":{"line":31,"column":23},"source":"../../models/userModel.js","original":{"line":29,"column":23}},{"generated":{"line":31,"column":65},"source":"../../models/userModel.js","original":{"line":29,"column":19}},{"generated":{"line":31,"column":66},"source":"../../models/userModel.js","original":{"line":26,"column":14}},{"name":"select","generated":{"line":32,"column":0},"source":"../../models/userModel.js","original":{"line":30,"column":8}},{"generated":{"line":32,"column":16},"source":"../../models/userModel.js","original":{"line":30,"column":16}},{"generated":{"line":33,"column":0},"source":"../../models/userModel.js","original":{"line":26,"column":14}},{"generated":{"line":33,"column":5},"source":"../../models/userModel.js","original":{"line":7,"column":39}},{"name":"passwordConfirm","generated":{"line":34,"column":0},"source":"../../models/userModel.js","original":{"line":32,"column":4}},{"generated":{"line":34,"column":21},"source":"../../models/userModel.js","original":{"line":32,"column":21}},{"name":"type","generated":{"line":35,"column":0},"source":"../../models/userModel.js","original":{"line":33,"column":8}},{"name":"String","generated":{"line":35,"column":14},"source":"../../models/userModel.js","original":{"line":33,"column":14}},{"generated":{"line":35,"column":20},"source":"../../models/userModel.js","original":{"line":32,"column":21}},{"name":"require","generated":{"line":36,"column":0},"source":"../../models/userModel.js","original":{"line":34,"column":8}},{"generated":{"line":36,"column":17},"source":"../../models/userModel.js","original":{"line":34,"column":17}},{"generated":{"line":36,"column":18},"source":"../../models/userModel.js","original":{"line":34,"column":18}},{"generated":{"line":36,"column":22},"source":"../../models/userModel.js","original":{"line":34,"column":17}},{"generated":{"line":36,"column":24},"source":"../../models/userModel.js","original":{"line":34,"column":24}},{"generated":{"line":36,"column":45},"source":"../../models/userModel.js","original":{"line":34,"column":17}},{"generated":{"line":36,"column":46},"source":"../../models/userModel.js","original":{"line":32,"column":21}},{"name":"validate","generated":{"line":37,"column":0},"source":"../../models/userModel.js","original":{"line":35,"column":8}},{"generated":{"line":37,"column":18},"source":"../../models/userModel.js","original":{"line":35,"column":18}},{"generated":{"line":38,"column":0},"source":"../../models/userModel.js","original":{"line":36,"column":12}},{"name":"validator","generated":{"line":39,"column":0},"source":"../../models/userModel.js","original":{"line":37,"column":12}},{"generated":{"line":39,"column":23},"source":"../../models/userModel.js","original":{"line":37,"column":23}},{"name":"el","generated":{"line":39,"column":42},"source":"../../models/userModel.js","original":{"line":37,"column":32}},{"generated":{"line":39,"column":44},"source":"../../models/userModel.js","original":{"line":37,"column":23}},{"generated":{"line":39,"column":46},"source":"../../models/userModel.js","original":{"line":37,"column":36}},{"generated":{"line":40,"column":0},"source":"../../models/userModel.js","original":{"line":38,"column":16}},{"name":"el","generated":{"line":40,"column":23},"source":"../../models/userModel.js","original":{"line":38,"column":23}},{"generated":{"line":40,"column":30},"source":"../../models/userModel.js","original":{"line":38,"column":30}},{"name":"password","generated":{"line":40,"column":35},"source":"../../models/userModel.js","original":{"line":38,"column":35}},{"generated":{"line":40,"column":43},"source":"../../models/userModel.js","original":{"line":38,"column":16}},{"generated":{"line":41,"column":0},"source":"../../models/userModel.js","original":{"line":39,"column":13}},{"generated":{"line":41,"column":13},"source":"../../models/userModel.js","original":{"line":35,"column":18}},{"name":"message","generated":{"line":42,"column":0},"source":"../../models/userModel.js","original":{"line":40,"column":12}},{"generated":{"line":42,"column":21},"source":"../../models/userModel.js","original":{"line":40,"column":21}},{"generated":{"line":43,"column":0},"source":"../../models/userModel.js","original":{"line":35,"column":18}},{"generated":{"line":44,"column":0},"source":"../../models/userModel.js","original":{"line":32,"column":21}},{"generated":{"line":44,"column":5},"source":"../../models/userModel.js","original":{"line":7,"column":39}},{"name":"passwordChangedAt","generated":{"line":45,"column":0},"source":"../../models/userModel.js","original":{"line":43,"column":4}},{"name":"Date","generated":{"line":45,"column":23},"source":"../../models/userModel.js","original":{"line":43,"column":23}},{"generated":{"line":45,"column":27},"source":"../../models/userModel.js","original":{"line":7,"column":39}},{"name":"passwordResetToken","generated":{"line":46,"column":0},"source":"../../models/userModel.js","original":{"line":44,"column":4}},{"name":"String","generated":{"line":46,"column":24},"source":"../../models/userModel.js","original":{"line":44,"column":24}},{"generated":{"line":46,"column":30},"source":"../../models/userModel.js","original":{"line":7,"column":39}},{"name":"passwordResetExpires","generated":{"line":47,"column":0},"source":"../../models/userModel.js","original":{"line":45,"column":4}},{"name":"Date","generated":{"line":47,"column":26},"source":"../../models/userModel.js","original":{"line":45,"column":26}},{"generated":{"line":47,"column":30},"source":"../../models/userModel.js","original":{"line":7,"column":39}},{"name":"active","generated":{"line":48,"column":0},"source":"../../models/userModel.js","original":{"line":46,"column":4}},{"generated":{"line":48,"column":12},"source":"../../models/userModel.js","original":{"line":46,"column":12}},{"name":"type","generated":{"line":49,"column":0},"source":"../../models/userModel.js","original":{"line":47,"column":8}},{"name":"Boolean","generated":{"line":49,"column":14},"source":"../../models/userModel.js","original":{"line":47,"column":14}},{"generated":{"line":49,"column":21},"source":"../../models/userModel.js","original":{"line":46,"column":12}},{"name":"default","generated":{"line":50,"column":0},"source":"../../models/userModel.js","original":{"line":48,"column":8}},{"generated":{"line":50,"column":17},"source":"../../models/userModel.js","original":{"line":48,"column":17}},{"generated":{"line":50,"column":21},"source":"../../models/userModel.js","original":{"line":46,"column":12}},{"name":"select","generated":{"line":51,"column":0},"source":"../../models/userModel.js","original":{"line":49,"column":8}},{"generated":{"line":51,"column":16},"source":"../../models/userModel.js","original":{"line":49,"column":16}},{"generated":{"line":51,"column":21},"source":"../../models/userModel.js","original":{"line":46,"column":12}},{"generated":{"line":51,"column":22},"source":"../../models/userModel.js","original":{"line":49,"column":22}},{"generated":{"line":52,"column":0},"source":"../../models/userModel.js","original":{"line":46,"column":12}},{"generated":{"line":53,"column":0},"source":"../../models/userModel.js","original":{"line":7,"column":39}},{"generated":{"line":53,"column":1},"source":"../../models/userModel.js","original":{"line":7,"column":19}},{"generated":{"line":53,"column":2},"source":"../../models/userModel.js","original":{"line":7,"column":0}},{"name":"userSchema","generated":{"line":55,"column":0},"source":"../../models/userModel.js","original":{"line":53,"column":0}},{"name":"pre","generated":{"line":55,"column":11},"source":"../../models/userModel.js","original":{"line":53,"column":11}},{"generated":{"line":55,"column":14},"source":"../../models/userModel.js","original":{"line":53,"column":0}},{"generated":{"line":55,"column":15},"source":"../../models/userModel.js","original":{"line":53,"column":15}},{"generated":{"line":55,"column":21},"source":"../../models/userModel.js","original":{"line":53,"column":0}},{"generated":{"line":56,"column":0},"source":"../../models/userModel.js","original":{"line":53,"column":0}},{"generated":{"line":56,"column":71},"source":"../../models/userModel.js","original":{"line":53,"column":23}},{"name":"next","generated":{"line":56,"column":88},"source":"../../models/userModel.js","original":{"line":53,"column":38}},{"generated":{"line":56,"column":92},"source":"../../models/userModel.js","original":{"line":53,"column":23}},{"generated":{"line":57,"column":0},"source":"../../models/userModel.js","original":{"line":53,"column":23}},{"generated":{"line":58,"column":0},"source":"../../models/userModel.js","original":{"line":53,"column":23}},{"generated":{"line":59,"column":0},"source":"../../models/userModel.js","original":{"line":53,"column":23}},{"generated":{"line":60,"column":0},"source":"../../models/userModel.js","original":{"line":53,"column":23}},{"generated":{"line":61,"column":0},"source":"../../models/userModel.js","original":{"line":53,"column":23}},{"generated":{"line":61,"column":28},"source":"../../models/userModel.js","original":{"line":55,"column":9}},{"name":"isModified","generated":{"line":61,"column":33},"source":"../../models/userModel.js","original":{"line":55,"column":14}},{"generated":{"line":61,"column":43},"source":"../../models/userModel.js","original":{"line":55,"column":9}},{"generated":{"line":61,"column":44},"source":"../../models/userModel.js","original":{"line":55,"column":25}},{"generated":{"line":61,"column":54},"source":"../../models/userModel.js","original":{"line":55,"column":9}},{"generated":{"line":61,"column":55},"source":"../../models/userModel.js","original":{"line":53,"column":23}},{"generated":{"line":62,"column":0},"source":"../../models/userModel.js","original":{"line":53,"column":23}},{"generated":{"line":63,"column":0},"source":"../../models/userModel.js","original":{"line":53,"column":23}},{"generated":{"line":64,"column":0},"source":"../../models/userModel.js","original":{"line":53,"column":23}},{"generated":{"line":66,"column":0},"source":"../../models/userModel.js","original":{"line":53,"column":23}},{"name":"next","generated":{"line":66,"column":57},"source":"../../models/userModel.js","original":{"line":55,"column":45}},{"generated":{"line":66,"column":63},"source":"../../models/userModel.js","original":{"line":53,"column":23}},{"generated":{"line":68,"column":0},"source":"../../models/userModel.js","original":{"line":53,"column":23}},{"generated":{"line":69,"column":0},"source":"../../models/userModel.js","original":{"line":53,"column":23}},{"generated":{"line":70,"column":0},"source":"../../models/userModel.js","original":{"line":53,"column":23}},{"name":"bcrypt","generated":{"line":70,"column":31},"source":"../../models/userModel.js","original":{"line":58,"column":26}},{"name":"hash","generated":{"line":70,"column":38},"source":"../../models/userModel.js","original":{"line":58,"column":33}},{"generated":{"line":70,"column":42},"source":"../../models/userModel.js","original":{"line":58,"column":26}},{"generated":{"line":70,"column":43},"source":"../../models/userModel.js","original":{"line":58,"column":38}},{"name":"password","generated":{"line":70,"column":48},"source":"../../models/userModel.js","original":{"line":58,"column":43}},{"generated":{"line":70,"column":56},"source":"../../models/userModel.js","original":{"line":58,"column":26}},{"generated":{"line":70,"column":58},"source":"../../models/userModel.js","original":{"line":58,"column":53}},{"generated":{"line":70,"column":60},"source":"../../models/userModel.js","original":{"line":58,"column":26}},{"generated":{"line":70,"column":61},"source":"../../models/userModel.js","original":{"line":53,"column":23}},{"generated":{"line":72,"column":0},"source":"../../models/userModel.js","original":{"line":53,"column":23}},{"generated":{"line":73,"column":0},"source":"../../models/userModel.js","original":{"line":58,"column":4}},{"name":"password","generated":{"line":73,"column":29},"source":"../../models/userModel.js","original":{"line":58,"column":9}},{"generated":{"line":73,"column":37},"source":"../../models/userModel.js","original":{"line":53,"column":23}},{"generated":{"line":76,"column":0},"source":"../../models/userModel.js","original":{"line":60,"column":4}},{"name":"passwordConfirm","generated":{"line":76,"column":29},"source":"../../models/userModel.js","original":{"line":60,"column":9}},{"generated":{"line":76,"column":44},"source":"../../models/userModel.js","original":{"line":60,"column":4}},{"name":"undefined","generated":{"line":76,"column":47},"source":"../../models/userModel.js","original":{"line":60,"column":27}},{"generated":{"line":76,"column":56},"source":"../../models/userModel.js","original":{"line":60,"column":4}},{"generated":{"line":76,"column":57},"source":"../../models/userModel.js","original":{"line":53,"column":23}},{"generated":{"line":76,"column":58},"source":"../../models/userModel.js","original":{"line":60,"column":38}},{"name":"next","generated":{"line":77,"column":0},"source":"../../models/userModel.js","original":{"line":61,"column":4}},{"generated":{"line":79,"column":0},"source":"../../models/userModel.js","original":{"line":53,"column":23}},{"generated":{"line":80,"column":0},"source":"../../models/userModel.js","original":{"line":53,"column":23}},{"generated":{"line":81,"column":0},"source":"../../models/userModel.js","original":{"line":53,"column":23}},{"generated":{"line":82,"column":0},"source":"../../models/userModel.js","original":{"line":53,"column":23}},{"generated":{"line":83,"column":0},"source":"../../models/userModel.js","original":{"line":53,"column":23}},{"generated":{"line":84,"column":0},"source":"../../models/userModel.js","original":{"line":53,"column":23}},{"generated":{"line":85,"column":0},"source":"../../models/userModel.js","original":{"line":53,"column":23}},{"generated":{"line":85,"column":5},"source":"../../models/userModel.js","original":{"line":53,"column":0}},{"generated":{"line":87,"column":0},"source":"../../models/userModel.js","original":{"line":53,"column":0}},{"generated":{"line":88,"column":0},"source":"../../models/userModel.js","original":{"line":53,"column":0}},{"generated":{"line":89,"column":0},"source":"../../models/userModel.js","original":{"line":53,"column":0}},{"generated":{"line":90,"column":0},"source":"../../models/userModel.js","original":{"line":53,"column":0}},{"name":"userSchema","generated":{"line":92,"column":0},"source":"../../models/userModel.js","original":{"line":64,"column":0}},{"name":"pre","generated":{"line":92,"column":11},"source":"../../models/userModel.js","original":{"line":64,"column":11}},{"generated":{"line":92,"column":14},"source":"../../models/userModel.js","original":{"line":64,"column":0}},{"generated":{"line":92,"column":15},"source":"../../models/userModel.js","original":{"line":64,"column":15}},{"generated":{"line":92,"column":21},"source":"../../models/userModel.js","original":{"line":64,"column":0}},{"generated":{"line":92,"column":23},"source":"../../models/userModel.js","original":{"line":64,"column":23}},{"name":"next","generated":{"line":92,"column":33},"source":"../../models/userModel.js","original":{"line":64,"column":33}},{"generated":{"line":92,"column":37},"source":"../../models/userModel.js","original":{"line":64,"column":23}},{"generated":{"line":92,"column":39},"source":"../../models/userModel.js","original":{"line":64,"column":39}},{"generated":{"line":93,"column":0},"source":"../../models/userModel.js","original":{"line":65,"column":4}},{"generated":{"line":93,"column":8},"source":"../../models/userModel.js","original":{"line":65,"column":8}},{"generated":{"line":93,"column":9},"source":"../../models/userModel.js","original":{"line":65,"column":9}},{"name":"isModified","generated":{"line":93,"column":14},"source":"../../models/userModel.js","original":{"line":65,"column":14}},{"generated":{"line":93,"column":24},"source":"../../models/userModel.js","original":{"line":65,"column":9}},{"generated":{"line":93,"column":25},"source":"../../models/userModel.js","original":{"line":65,"column":25}},{"generated":{"line":93,"column":35},"source":"../../models/userModel.js","original":{"line":65,"column":9}},{"generated":{"line":93,"column":36},"source":"../../models/userModel.js","original":{"line":65,"column":8}},{"generated":{"line":93,"column":40},"source":"../../models/userModel.js","original":{"line":65,"column":40}},{"name":"isNew","generated":{"line":93,"column":45},"source":"../../models/userModel.js","original":{"line":65,"column":45}},{"generated":{"line":93,"column":50},"source":"../../models/userModel.js","original":{"line":65,"column":4}},{"generated":{"line":93,"column":52},"source":"../../models/userModel.js","original":{"line":65,"column":52}},{"name":"next","generated":{"line":93,"column":59},"source":"../../models/userModel.js","original":{"line":65,"column":59}},{"generated":{"line":93,"column":65},"source":"../../models/userModel.js","original":{"line":65,"column":52}},{"generated":{"line":95,"column":0},"source":"../../models/userModel.js","original":{"line":67,"column":4}},{"name":"passwordChangedAt","generated":{"line":95,"column":9},"source":"../../models/userModel.js","original":{"line":67,"column":9}},{"generated":{"line":95,"column":26},"source":"../../models/userModel.js","original":{"line":67,"column":4}},{"name":"Date","generated":{"line":95,"column":29},"source":"../../models/userModel.js","original":{"line":67,"column":29}},{"name":"now","generated":{"line":95,"column":34},"source":"../../models/userModel.js","original":{"line":67,"column":34}},{"generated":{"line":95,"column":37},"source":"../../models/userModel.js","original":{"line":67,"column":29}},{"generated":{"line":95,"column":42},"source":"../../models/userModel.js","original":{"line":67,"column":40}},{"generated":{"line":95,"column":46},"source":"../../models/userModel.js","original":{"line":67,"column":4}},{"name":"next","generated":{"line":96,"column":0},"source":"../../models/userModel.js","original":{"line":68,"column":4}},{"generated":{"line":97,"column":0},"source":"../../models/userModel.js","original":{"line":69,"column":3}},{"generated":{"line":97,"column":1},"source":"../../models/userModel.js","original":{"line":64,"column":0}},{"name":"userSchema","generated":{"line":99,"column":0},"source":"../../models/userModel.js","original":{"line":72,"column":0}},{"name":"pre","generated":{"line":99,"column":11},"source":"../../models/userModel.js","original":{"line":72,"column":11}},{"generated":{"line":99,"column":14},"source":"../../models/userModel.js","original":{"line":72,"column":0}},{"generated":{"line":99,"column":15},"source":"../../models/userModel.js","original":{"line":72,"column":15}},{"generated":{"line":99,"column":22},"source":"../../models/userModel.js","original":{"line":72,"column":0}},{"generated":{"line":99,"column":24},"source":"../../models/userModel.js","original":{"line":72,"column":24}},{"name":"next","generated":{"line":99,"column":34},"source":"../../models/userModel.js","original":{"line":72,"column":33}},{"generated":{"line":99,"column":38},"source":"../../models/userModel.js","original":{"line":72,"column":24}},{"generated":{"line":99,"column":40},"source":"../../models/userModel.js","original":{"line":72,"column":39}},{"generated":{"line":100,"column":0},"source":"../../models/userModel.js","original":{"line":73,"column":4}},{"generated":{"line":101,"column":0},"source":"../../models/userModel.js","original":{"line":74,"column":4}},{"name":"find","generated":{"line":101,"column":9},"source":"../../models/userModel.js","original":{"line":74,"column":9}},{"generated":{"line":101,"column":13},"source":"../../models/userModel.js","original":{"line":74,"column":4}},{"generated":{"line":101,"column":14},"source":"../../models/userModel.js","original":{"line":74,"column":14}},{"name":"active","generated":{"line":101,"column":16},"source":"../../models/userModel.js","original":{"line":74,"column":15}},{"generated":{"line":101,"column":24},"source":"../../models/userModel.js","original":{"line":74,"column":23}},{"name":"$ne","generated":{"line":101,"column":26},"source":"../../models/userModel.js","original":{"line":74,"column":24}},{"generated":{"line":101,"column":31},"source":"../../models/userModel.js","original":{"line":74,"column":29}},{"generated":{"line":101,"column":36},"source":"../../models/userModel.js","original":{"line":74,"column":23}},{"generated":{"line":101,"column":38},"source":"../../models/userModel.js","original":{"line":74,"column":14}},{"generated":{"line":101,"column":40},"source":"../../models/userModel.js","original":{"line":74,"column":4}},{"name":"next","generated":{"line":102,"column":0},"source":"../../models/userModel.js","original":{"line":75,"column":4}},{"generated":{"line":103,"column":0},"source":"../../models/userModel.js","original":{"line":76,"column":1}},{"generated":{"line":103,"column":1},"source":"../../models/userModel.js","original":{"line":72,"column":0}},{"generated":{"line":104,"column":0},"source":"../../models/userModel.js","original":{"line":77,"column":0}},{"name":"userSchema","generated":{"line":105,"column":0},"source":"../../models/userModel.js","original":{"line":78,"column":0}},{"name":"methods","generated":{"line":105,"column":11},"source":"../../models/userModel.js","original":{"line":78,"column":11}},{"generated":{"line":105,"column":18},"source":"../../models/userModel.js","original":{"line":78,"column":0}},{"name":"correctPassword","generated":{"line":105,"column":19},"source":"../../models/userModel.js","original":{"line":78,"column":19}},{"generated":{"line":105,"column":34},"source":"../../models/userModel.js","original":{"line":78,"column":0}},{"generated":{"line":106,"column":0},"source":"../../models/userModel.js","original":{"line":78,"column":0}},{"generated":{"line":106,"column":72},"source":"../../models/userModel.js","original":{"line":78,"column":37}},{"name":"candidatePassword","generated":{"line":106,"column":90},"source":"../../models/userModel.js","original":{"line":78,"column":52}},{"generated":{"line":106,"column":107},"source":"../../models/userModel.js","original":{"line":78,"column":37}},{"name":"userPassword","generated":{"line":106,"column":109},"source":"../../models/userModel.js","original":{"line":78,"column":71}},{"generated":{"line":106,"column":121},"source":"../../models/userModel.js","original":{"line":78,"column":37}},{"generated":{"line":107,"column":0},"source":"../../models/userModel.js","original":{"line":78,"column":37}},{"generated":{"line":108,"column":0},"source":"../../models/userModel.js","original":{"line":78,"column":37}},{"generated":{"line":109,"column":0},"source":"../../models/userModel.js","original":{"line":78,"column":37}},{"generated":{"line":110,"column":0},"source":"../../models/userModel.js","original":{"line":78,"column":37}},{"generated":{"line":111,"column":0},"source":"../../models/userModel.js","original":{"line":78,"column":37}},{"generated":{"line":112,"column":0},"source":"../../models/userModel.js","original":{"line":78,"column":37}},{"name":"bcrypt","generated":{"line":112,"column":31},"source":"../../models/userModel.js","original":{"line":79,"column":17}},{"name":"compare","generated":{"line":112,"column":38},"source":"../../models/userModel.js","original":{"line":79,"column":24}},{"generated":{"line":112,"column":45},"source":"../../models/userModel.js","original":{"line":79,"column":17}},{"name":"candidatePassword","generated":{"line":112,"column":46},"source":"../../models/userModel.js","original":{"line":79,"column":32}},{"generated":{"line":112,"column":63},"source":"../../models/userModel.js","original":{"line":79,"column":17}},{"name":"userPassword","generated":{"line":112,"column":65},"source":"../../models/userModel.js","original":{"line":79,"column":51}},{"generated":{"line":112,"column":77},"source":"../../models/userModel.js","original":{"line":79,"column":17}},{"generated":{"line":112,"column":78},"source":"../../models/userModel.js","original":{"line":78,"column":37}},{"generated":{"line":114,"column":0},"source":"../../models/userModel.js","original":{"line":78,"column":37}},{"generated":{"line":115,"column":0},"source":"../../models/userModel.js","original":{"line":78,"column":37}},{"generated":{"line":117,"column":0},"source":"../../models/userModel.js","original":{"line":78,"column":37}},{"generated":{"line":118,"column":0},"source":"../../models/userModel.js","original":{"line":78,"column":37}},{"generated":{"line":119,"column":0},"source":"../../models/userModel.js","original":{"line":78,"column":37}},{"generated":{"line":120,"column":0},"source":"../../models/userModel.js","original":{"line":78,"column":37}},{"generated":{"line":121,"column":0},"source":"../../models/userModel.js","original":{"line":78,"column":37}},{"generated":{"line":122,"column":0},"source":"../../models/userModel.js","original":{"line":78,"column":37}},{"generated":{"line":123,"column":0},"source":"../../models/userModel.js","original":{"line":78,"column":37}},{"generated":{"line":123,"column":5},"source":"../../models/userModel.js","original":{"line":78,"column":0}},{"generated":{"line":125,"column":0},"source":"../../models/userModel.js","original":{"line":78,"column":0}},{"generated":{"line":126,"column":0},"source":"../../models/userModel.js","original":{"line":78,"column":0}},{"generated":{"line":127,"column":0},"source":"../../models/userModel.js","original":{"line":78,"column":0}},{"generated":{"line":128,"column":0},"source":"../../models/userModel.js","original":{"line":78,"column":0}},{"name":"userSchema","generated":{"line":130,"column":0},"source":"../../models/userModel.js","original":{"line":82,"column":0}},{"name":"methods","generated":{"line":130,"column":11},"source":"../../models/userModel.js","original":{"line":82,"column":11}},{"generated":{"line":130,"column":18},"source":"../../models/userModel.js","original":{"line":82,"column":0}},{"name":"changePasswordAfter","generated":{"line":130,"column":19},"source":"../../models/userModel.js","original":{"line":82,"column":19}},{"generated":{"line":130,"column":38},"source":"../../models/userModel.js","original":{"line":82,"column":0}},{"generated":{"line":130,"column":41},"source":"../../models/userModel.js","original":{"line":82,"column":41}},{"name":"JWTTimestamp","generated":{"line":130,"column":51},"source":"../../models/userModel.js","original":{"line":82,"column":50}},{"generated":{"line":130,"column":63},"source":"../../models/userModel.js","original":{"line":82,"column":41}},{"generated":{"line":130,"column":65},"source":"../../models/userModel.js","original":{"line":82,"column":64}},{"generated":{"line":131,"column":0},"source":"../../models/userModel.js","original":{"line":83,"column":4}},{"generated":{"line":131,"column":8},"source":"../../models/userModel.js","original":{"line":83,"column":8}},{"name":"passwordChangedAt","generated":{"line":131,"column":13},"source":"../../models/userModel.js","original":{"line":83,"column":13}},{"generated":{"line":131,"column":30},"source":"../../models/userModel.js","original":{"line":83,"column":4}},{"generated":{"line":131,"column":32},"source":"../../models/userModel.js","original":{"line":83,"column":31}},{"generated":{"line":132,"column":0},"source":"../../models/userModel.js","original":{"line":84,"column":8}},{"name":"changedTimestamp","generated":{"line":132,"column":12},"source":"../../models/userModel.js","original":{"line":84,"column":14}},{"name":"parseInt","generated":{"line":132,"column":31},"source":"../../models/userModel.js","original":{"line":84,"column":33}},{"generated":{"line":132,"column":40},"source":"../../models/userModel.js","original":{"line":85,"column":12}},{"name":"passwordChangedAt","generated":{"line":132,"column":45},"source":"../../models/userModel.js","original":{"line":85,"column":17}},{"generated":{"line":132,"column":62},"source":"../../models/userModel.js","original":{"line":85,"column":12}},{"name":"getTime","generated":{"line":132,"column":63},"source":"../../models/userModel.js","original":{"line":85,"column":35}},{"generated":{"line":132,"column":70},"source":"../../models/userModel.js","original":{"line":85,"column":12}},{"generated":{"line":132,"column":75},"source":"../../models/userModel.js","original":{"line":85,"column":47}},{"generated":{"line":132,"column":79},"source":"../../models/userModel.js","original":{"line":84,"column":33}},{"generated":{"line":132,"column":81},"source":"../../models/userModel.js","original":{"line":86,"column":12}},{"generated":{"line":132,"column":83},"source":"../../models/userModel.js","original":{"line":84,"column":33}},{"generated":{"line":132,"column":84},"source":"../../models/userModel.js","original":{"line":84,"column":8}},{"generated":{"line":134,"column":0},"source":"../../models/userModel.js","original":{"line":89,"column":8}},{"name":"JWTTimestamp","generated":{"line":134,"column":15},"source":"../../models/userModel.js","original":{"line":89,"column":15}},{"name":"changedTimestamp","generated":{"line":134,"column":30},"source":"../../models/userModel.js","original":{"line":89,"column":30}},{"generated":{"line":134,"column":46},"source":"../../models/userModel.js","original":{"line":89,"column":8}},{"generated":{"line":134,"column":47},"source":"../../models/userModel.js","original":{"line":83,"column":31}},{"generated":{"line":134,"column":48},"source":"../../models/userModel.js","original":{"line":89,"column":48}},{"generated":{"line":135,"column":0},"source":"../../models/userModel.js","original":{"line":90,"column":5}},{"generated":{"line":136,"column":0},"source":"../../models/userModel.js","original":{"line":91,"column":4}},{"generated":{"line":136,"column":11},"source":"../../models/userModel.js","original":{"line":91,"column":11}},{"generated":{"line":136,"column":16},"source":"../../models/userModel.js","original":{"line":91,"column":4}},{"generated":{"line":136,"column":17},"source":"../../models/userModel.js","original":{"line":82,"column":64}},{"generated":{"line":136,"column":18},"source":"../../models/userModel.js","original":{"line":91,"column":18}},{"generated":{"line":137,"column":0},"source":"../../models/userModel.js","original":{"line":92,"column":1}},{"generated":{"line":137,"column":1},"source":"../../models/userModel.js","original":{"line":82,"column":0}},{"name":"userSchema","generated":{"line":139,"column":0},"source":"../../models/userModel.js","original":{"line":94,"column":0}},{"name":"methods","generated":{"line":139,"column":11},"source":"../../models/userModel.js","original":{"line":94,"column":11}},{"generated":{"line":139,"column":18},"source":"../../models/userModel.js","original":{"line":94,"column":0}},{"name":"createPasswordResetToken","generated":{"line":139,"column":19},"source":"../../models/userModel.js","original":{"line":94,"column":19}},{"generated":{"line":139,"column":43},"source":"../../models/userModel.js","original":{"line":94,"column":0}},{"generated":{"line":139,"column":46},"source":"../../models/userModel.js","original":{"line":94,"column":46}},{"generated":{"line":139,"column":58},"source":"../../models/userModel.js","original":{"line":94,"column":57}},{"generated":{"line":140,"column":0},"source":"../../models/userModel.js","original":{"line":95,"column":4}},{"name":"resetToken","generated":{"line":140,"column":8},"source":"../../models/userModel.js","original":{"line":95,"column":10}},{"name":"crypto","generated":{"line":140,"column":21},"source":"../../models/userModel.js","original":{"line":95,"column":23}},{"name":"randomBytes","generated":{"line":140,"column":28},"source":"../../models/userModel.js","original":{"line":95,"column":30}},{"generated":{"line":140,"column":39},"source":"../../models/userModel.js","original":{"line":95,"column":23}},{"generated":{"line":140,"column":40},"source":"../../models/userModel.js","original":{"line":95,"column":42}},{"generated":{"line":140,"column":42},"source":"../../models/userModel.js","original":{"line":95,"column":23}},{"name":"toString","generated":{"line":140,"column":44},"source":"../../models/userModel.js","original":{"line":95,"column":46}},{"generated":{"line":140,"column":52},"source":"../../models/userModel.js","original":{"line":95,"column":23}},{"generated":{"line":140,"column":53},"source":"../../models/userModel.js","original":{"line":95,"column":55}},{"generated":{"line":140,"column":58},"source":"../../models/userModel.js","original":{"line":95,"column":23}},{"generated":{"line":140,"column":59},"source":"../../models/userModel.js","original":{"line":95,"column":4}},{"generated":{"line":142,"column":0},"source":"../../models/userModel.js","original":{"line":97,"column":4}},{"name":"passwordResetToken","generated":{"line":142,"column":9},"source":"../../models/userModel.js","original":{"line":97,"column":9}},{"generated":{"line":142,"column":27},"source":"../../models/userModel.js","original":{"line":97,"column":4}},{"name":"crypto","generated":{"line":142,"column":30},"source":"../../models/userModel.js","original":{"line":97,"column":30}},{"name":"createHash","generated":{"line":142,"column":37},"source":"../../models/userModel.js","original":{"line":98,"column":5}},{"generated":{"line":142,"column":47},"source":"../../models/userModel.js","original":{"line":97,"column":30}},{"generated":{"line":142,"column":48},"source":"../../models/userModel.js","original":{"line":98,"column":16}},{"generated":{"line":142,"column":56},"source":"../../models/userModel.js","original":{"line":97,"column":30}},{"name":"update","generated":{"line":142,"column":58},"source":"../../models/userModel.js","original":{"line":99,"column":5}},{"generated":{"line":142,"column":64},"source":"../../models/userModel.js","original":{"line":97,"column":30}},{"name":"resetToken","generated":{"line":142,"column":65},"source":"../../models/userModel.js","original":{"line":99,"column":12}},{"generated":{"line":142,"column":75},"source":"../../models/userModel.js","original":{"line":97,"column":30}},{"name":"digest","generated":{"line":142,"column":77},"source":"../../models/userModel.js","original":{"line":99,"column":24}},{"generated":{"line":142,"column":83},"source":"../../models/userModel.js","original":{"line":97,"column":30}},{"generated":{"line":142,"column":84},"source":"../../models/userModel.js","original":{"line":99,"column":31}},{"generated":{"line":142,"column":89},"source":"../../models/userModel.js","original":{"line":97,"column":30}},{"generated":{"line":142,"column":90},"source":"../../models/userModel.js","original":{"line":97,"column":4}},{"name":"console","generated":{"line":144,"column":0},"source":"../../models/userModel.js","original":{"line":101,"column":4}},{"name":"log","generated":{"line":144,"column":12},"source":"../../models/userModel.js","original":{"line":101,"column":12}},{"generated":{"line":144,"column":15},"source":"../../models/userModel.js","original":{"line":101,"column":4}},{"generated":{"line":144,"column":16},"source":"../../models/userModel.js","original":{"line":101,"column":16}},{"name":"resetToken","generated":{"line":144,"column":18},"source":"../../models/userModel.js","original":{"line":101,"column":17}},{"generated":{"line":144,"column":40},"source":"../../models/userModel.js","original":{"line":101,"column":16}},{"generated":{"line":144,"column":42},"source":"../../models/userModel.js","original":{"line":101,"column":4}},{"generated":{"line":144,"column":44},"source":"../../models/userModel.js","original":{"line":101,"column":30}},{"name":"passwordResetToken","generated":{"line":144,"column":49},"source":"../../models/userModel.js","original":{"line":101,"column":35}},{"generated":{"line":144,"column":67},"source":"../../models/userModel.js","original":{"line":101,"column":4}},{"generated":{"line":146,"column":0},"source":"../../models/userModel.js","original":{"line":103,"column":4}},{"name":"passwordResetExpires","generated":{"line":146,"column":9},"source":"../../models/userModel.js","original":{"line":103,"column":9}},{"generated":{"line":146,"column":29},"source":"../../models/userModel.js","original":{"line":103,"column":4}},{"name":"Date","generated":{"line":146,"column":32},"source":"../../models/userModel.js","original":{"line":103,"column":32}},{"name":"now","generated":{"line":146,"column":37},"source":"../../models/userModel.js","original":{"line":103,"column":37}},{"generated":{"line":146,"column":40},"source":"../../models/userModel.js","original":{"line":103,"column":32}},{"generated":{"line":146,"column":45},"source":"../../models/userModel.js","original":{"line":103,"column":45}},{"generated":{"line":146,"column":50},"source":"../../models/userModel.js","original":{"line":103,"column":48}},{"generated":{"line":146,"column":52},"source":"../../models/userModel.js","original":{"line":103,"column":45}},{"generated":{"line":146,"column":55},"source":"../../models/userModel.js","original":{"line":103,"column":51}},{"generated":{"line":146,"column":59},"source":"../../models/userModel.js","original":{"line":103,"column":4}},{"generated":{"line":148,"column":0},"source":"../../models/userModel.js","original":{"line":105,"column":4}},{"name":"resetToken","generated":{"line":148,"column":11},"source":"../../models/userModel.js","original":{"line":105,"column":11}},{"generated":{"line":148,"column":21},"source":"../../models/userModel.js","original":{"line":105,"column":4}},{"generated":{"line":149,"column":0},"source":"../../models/userModel.js","original":{"line":106,"column":1}},{"generated":{"line":149,"column":1},"source":"../../models/userModel.js","original":{"line":94,"column":0}},{"generated":{"line":150,"column":0},"source":"../../models/userModel.js","original":{"line":107,"column":0}},{"name":"User","generated":{"line":150,"column":4},"source":"../../models/userModel.js","original":{"line":107,"column":6}},{"name":"mongoose","generated":{"line":150,"column":11},"source":"../../models/userModel.js","original":{"line":107,"column":13}},{"name":"model","generated":{"line":150,"column":20},"source":"../../models/userModel.js","original":{"line":107,"column":22}},{"generated":{"line":150,"column":25},"source":"../../models/userModel.js","original":{"line":107,"column":13}},{"generated":{"line":150,"column":26},"source":"../../models/userModel.js","original":{"line":107,"column":28}},{"generated":{"line":150,"column":32},"source":"../../models/userModel.js","original":{"line":107,"column":13}},{"name":"userSchema","generated":{"line":150,"column":34},"source":"../../models/userModel.js","original":{"line":107,"column":36}},{"generated":{"line":150,"column":44},"source":"../../models/userModel.js","original":{"line":107,"column":13}},{"generated":{"line":150,"column":45},"source":"../../models/userModel.js","original":{"line":107,"column":0}},{"name":"module","generated":{"line":151,"column":0},"source":"../../models/userModel.js","original":{"line":108,"column":0}},{"name":"exports","generated":{"line":151,"column":7},"source":"../../models/userModel.js","original":{"line":108,"column":7}},{"generated":{"line":151,"column":14},"source":"../../models/userModel.js","original":{"line":108,"column":0}},{"name":"User","generated":{"line":151,"column":17},"source":"../../models/userModel.js","original":{"line":108,"column":17}},{"generated":{"line":151,"column":21},"source":"../../models/userModel.js","original":{"line":108,"column":0}}],"sources":{"../../models/userModel.js":"const mongoose = require('mongoose');\nconst slugify = require('slugify');\nconst validator = require('validator');\nconst bcrypt = require('bcryptjs')\nconst crypto = require('crypto')\n\nconst userSchema = new mongoose.Schema({\n    name: {\n        type: String,\n        require: [true, 'Name is required'],\n        trim: true\n    },\n    email: {\n        type: String,\n        require: [true, 'Email is required'],\n        unique: true,\n        lowercase: true,\n        validate: [validator.isEmail, 'Email is invalid']\n    },\n    photo: String,\n    role: {\n        type: String,\n        enum: ['user','guide','lead-guide', 'admin'],\n        default: 'user'\n    },\n    password: {\n        type: String,\n        require: [true, 'Password is required'],\n        minlength: [8, 'Password must have at least 8 characters'],\n        select: false \n    },\n    passwordConfirm: {\n        type: String,\n        require: [true, 'Password must match'],\n        validate: {\n            // only work on CREATE and SAVE\n            validator: function(el) {\n                return el === this.password; \n            },\n            message: 'Passwords are not the same'\n        }\n    },\n    passwordChangedAt: Date,\n    passwordResetToken: String,\n    passwordResetExpires: Date ,\n    active: {\n        type: Boolean,\n        default: true,\n        select: false // not showing it to anyone\n    }\n})\n\nuserSchema.pre('save', async function(next) {\n    // only run this password if password was actually modified\n    if (!this.isModified('password')) return next(); \n\n    // hash the password with cost 12\n    this.password = await bcrypt.hash(this.password, 12)\n\n    this.passwordConfirm = undefined; // not to be persisted to the database \n    next(); \n}) \n\nuserSchema.pre('save', function (next) {\n    if (!this.isModified('password') || this.isNew) return next();\n\n    this.passwordChangedAt = Date.now()-1000;\n    next(); \n  });\n\n\nuserSchema.pre(/^find/, function(next) {\n    // this points to the current query\n    this.find({active: {$ne: false}});\n    next(); \n})\n// instant function, available on all models \nuserSchema.methods.correctPassword = async function(candidatePassword, userPassword) {\n    return await bcrypt.compare(candidatePassword, userPassword); \n}\n\nuserSchema.methods.changePasswordAfter = function(JWTTimestamp) {\n    if (this.passwordChangedAt){\n        const changedTimestamp = parseInt(\n            this.passwordChangedAt.getTime() / 1000,\n            10\n        )\n       \n        return JWTTimestamp < changedTimestamp; // token creation time < password change time -> password was changed!\n    }\n    return false; // the user hasn't changed the pass after this timestamp\n}\n\nuserSchema.methods.createPasswordResetToken = function() {\n    const resetToken = crypto.randomBytes(32).toString('hex'); \n\n    this.passwordResetToken = crypto\n    .createHash('sha256')\n    .update(resetToken).digest('hex'); \n\n    console.log({resetToken}, this.passwordResetToken);\n\n    this.passwordResetExpires = Date.now() + 10*60*1000;\n\n    return resetToken; \n}\nconst User = mongoose.model('User', userSchema)\nmodule.exports = User "},"lineCount":null}},"hash":"cd3ec5e0d368c4a78c2727fb55912728","cacheData":{"env":{}}}