{"id":"../../utils/appError.js","dependencies":[{"name":"/Users/hieungannguyen/Dropbox/Mac/Documents/vn-tours/package.json","includedInParent":true,"mtime":1652461384140}],"generated":{"js":"function _classCallCheck(instance, Constructor) { if (!(instance instanceof Constructor)) { throw new TypeError(\"Cannot call a class as a function\"); } }\n\nfunction _possibleConstructorReturn(self, call) { if (!self) { throw new ReferenceError(\"this hasn't been initialised - super() hasn't been called\"); } return call && (typeof call === \"object\" || typeof call === \"function\") ? call : self; }\n\nfunction _inherits(subClass, superClass) { if (typeof superClass !== \"function\" && superClass !== null) { throw new TypeError(\"Super expression must either be null or a function, not \" + typeof superClass); } subClass.prototype = Object.create(superClass && superClass.prototype, { constructor: { value: subClass, enumerable: false, writable: true, configurable: true } }); if (superClass) Object.setPrototypeOf ? Object.setPrototypeOf(subClass, superClass) : subClass.__proto__ = superClass; }\n\n/* operational errors - errors that we can predict */\n\nvar AppError = function (_Error) {\n    _inherits(AppError, _Error);\n\n    function AppError(message, statusCode) {\n        _classCallCheck(this, AppError);\n\n        var _this = _possibleConstructorReturn(this, (AppError.__proto__ || Object.getPrototypeOf(AppError)).call(this, message));\n\n        _this.statusCode = statusCode;\n        _this.status = ('' + statusCode).startsWith('4') ? 'fail' : 'error';\n        _this.isOperational = true;\n\n        Error.captureStackTrace(_this, _this.constructor);\n        return _this;\n    }\n\n    return AppError;\n}(Error);\n\nmodule.exports = AppError;","map":{"mappings":[{"generated":{"line":7,"column":0},"source":"../../utils/appError.js","original":{"line":1,"column":0}},{"name":"AppError","generated":{"line":9,"column":4},"source":"../../utils/appError.js","original":{"line":3,"column":6}},{"generated":{"line":12,"column":0},"source":"../../utils/appError.js","original":{"line":4,"column":4}},{"name":"message","generated":{"line":12,"column":22},"source":"../../utils/appError.js","original":{"line":4,"column":16}},{"generated":{"line":12,"column":29},"source":"../../utils/appError.js","original":{"line":4,"column":4}},{"name":"statusCode","generated":{"line":12,"column":31},"source":"../../utils/appError.js","original":{"line":4,"column":25}},{"generated":{"line":12,"column":41},"source":"../../utils/appError.js","original":{"line":4,"column":4}},{"generated":{"line":12,"column":43},"source":"../../utils/appError.js","original":{"line":4,"column":37}},{"generated":{"line":13,"column":0},"source":"../../utils/appError.js","original":{"line":4,"column":37}},{"generated":{"line":15,"column":0},"source":"../../utils/appError.js","original":{"line":4,"column":37}},{"name":"message","generated":{"line":15,"column":120},"source":"../../utils/appError.js","original":{"line":5,"column":14}},{"generated":{"line":15,"column":127},"source":"../../utils/appError.js","original":{"line":4,"column":37}},{"generated":{"line":17,"column":0},"source":"../../utils/appError.js","original":{"line":7,"column":8}},{"name":"statusCode","generated":{"line":17,"column":14},"source":"../../utils/appError.js","original":{"line":7,"column":13}},{"generated":{"line":17,"column":24},"source":"../../utils/appError.js","original":{"line":7,"column":8}},{"name":"statusCode","generated":{"line":17,"column":27},"source":"../../utils/appError.js","original":{"line":7,"column":26}},{"generated":{"line":17,"column":37},"source":"../../utils/appError.js","original":{"line":7,"column":8}},{"generated":{"line":18,"column":0},"source":"../../utils/appError.js","original":{"line":8,"column":8}},{"name":"status","generated":{"line":18,"column":14},"source":"../../utils/appError.js","original":{"line":8,"column":13}},{"generated":{"line":18,"column":20},"source":"../../utils/appError.js","original":{"line":8,"column":8}},{"generated":{"line":18,"column":23},"source":"../../utils/appError.js","original":{"line":8,"column":22}},{"name":"statusCode","generated":{"line":18,"column":29},"source":"../../utils/appError.js","original":{"line":8,"column":25}},{"generated":{"line":18,"column":39},"source":"../../utils/appError.js","original":{"line":8,"column":22}},{"name":"startsWith","generated":{"line":18,"column":41},"source":"../../utils/appError.js","original":{"line":8,"column":38}},{"generated":{"line":18,"column":51},"source":"../../utils/appError.js","original":{"line":8,"column":22}},{"generated":{"line":18,"column":52},"source":"../../utils/appError.js","original":{"line":8,"column":49}},{"generated":{"line":18,"column":55},"source":"../../utils/appError.js","original":{"line":8,"column":22}},{"generated":{"line":18,"column":59},"source":"../../utils/appError.js","original":{"line":8,"column":56}},{"generated":{"line":18,"column":65},"source":"../../utils/appError.js","original":{"line":8,"column":22}},{"generated":{"line":18,"column":68},"source":"../../utils/appError.js","original":{"line":8,"column":65}},{"generated":{"line":18,"column":75},"source":"../../utils/appError.js","original":{"line":8,"column":8}},{"generated":{"line":19,"column":0},"source":"../../utils/appError.js","original":{"line":9,"column":8}},{"name":"isOperational","generated":{"line":19,"column":14},"source":"../../utils/appError.js","original":{"line":9,"column":13}},{"generated":{"line":19,"column":27},"source":"../../utils/appError.js","original":{"line":9,"column":8}},{"generated":{"line":19,"column":30},"source":"../../utils/appError.js","original":{"line":9,"column":29}},{"generated":{"line":19,"column":34},"source":"../../utils/appError.js","original":{"line":9,"column":8}},{"name":"Error","generated":{"line":21,"column":0},"source":"../../utils/appError.js","original":{"line":11,"column":8}},{"name":"captureStackTrace","generated":{"line":21,"column":14},"source":"../../utils/appError.js","original":{"line":11,"column":14}},{"generated":{"line":21,"column":31},"source":"../../utils/appError.js","original":{"line":11,"column":8}},{"generated":{"line":21,"column":39},"source":"../../utils/appError.js","original":{"line":11,"column":38}},{"name":"constructor","generated":{"line":21,"column":45},"source":"../../utils/appError.js","original":{"line":11,"column":43}},{"generated":{"line":21,"column":56},"source":"../../utils/appError.js","original":{"line":11,"column":8}},{"generated":{"line":22,"column":0},"source":"../../utils/appError.js","original":{"line":4,"column":37}},{"generated":{"line":23,"column":0},"source":"../../utils/appError.js","original":{"line":12,"column":5}},{"name":"Error","generated":{"line":26,"column":2},"source":"../../utils/appError.js","original":{"line":3,"column":23}},{"name":"module","generated":{"line":28,"column":0},"source":"../../utils/appError.js","original":{"line":15,"column":0}},{"name":"exports","generated":{"line":28,"column":7},"source":"../../utils/appError.js","original":{"line":15,"column":7}},{"generated":{"line":28,"column":14},"source":"../../utils/appError.js","original":{"line":15,"column":0}},{"name":"AppError","generated":{"line":28,"column":17},"source":"../../utils/appError.js","original":{"line":15,"column":17}},{"generated":{"line":28,"column":25},"source":"../../utils/appError.js","original":{"line":15,"column":0}}],"sources":{"../../utils/appError.js":"/* operational errors - errors that we can predict */\n\nclass AppError extends Error {\n    constructor(message, statusCode) {\n        super(message);\n\n        this.statusCode = statusCode;\n        this.status = `${statusCode}`.startsWith('4') ? 'fail' : 'error';\n        this.isOperational = true \n\n        Error.captureStackTrace(this, this.constructor);\n    }\n}\n\nmodule.exports = AppError; "},"lineCount":null}},"hash":"30433d992ef5b7e187fe42ece1fc80e9","cacheData":{"env":{}}}